interval_tool/__init__.py
interval_tool/_impl.py
interval_tool-0.1.0.dist-info/WHEEL
interval_tool-0.1.0.dist-info/METADATA
interval_tool-0.1.0.dist-info/RECORD
