Metadata-Version: 2.1
Name: interval-tool
Version: 0.1.0
Summary: 
Author: Incomplete
Author-email: incomplete@aixon.co
Requires-Python: >=3.6
Classifier: Programming Language :: Python :: 3
Classifier: Programming Language :: Python :: 3.6
Classifier: Programming Language :: Python :: 3.7
Classifier: Programming Language :: Python :: 3.8
Classifier: Programming Language :: Python :: 3.9
Requires-Dist: tail-recursion (>=1.1.1)
